setup.py
gaus_dist/Binomialdistribution.py
gaus_dist/Gaussiandistribution.py
gaus_dist/Generaldistribution.py
gaus_dist/__init__.py
gaus_dist.egg-info/PKG-INFO
gaus_dist.egg-info/SOURCES.txt
gaus_dist.egg-info/dependency_links.txt
gaus_dist.egg-info/not-zip-safe
gaus_dist.egg-info/top_level.txt