Metadata-Version: 1.0
Name: gaus-dist
Version: 1.0
Summary: Gaussian and Binomial distributions
Home-page: UNKNOWN
Author: Ariyo Sanmi
Author-email: sanmi4ariyo@gmail.com
License: UNKNOWN
Platform: UNKNOWN
